LICENSE
README.md
setup.py
canvashanddraw/__init__.py
canvashanddraw/color.py
canvashanddraw/drawhelper.py
canvashanddraw/main.py
canvashanddraw/points.py
canvashanddraw/version.py
canvashanddraw.egg-info/PKG-INFO
canvashanddraw.egg-info/SOURCES.txt
canvashanddraw.egg-info/dependency_links.txt
canvashanddraw.egg-info/entry_points.txt
canvashanddraw.egg-info/requires.txt
canvashanddraw.egg-info/top_level.txt