Metadata-Version: 2.1
Name: canvashanddraw
Version: 1.0.0
Summary: A package to draw a set of points in a canvas, and save it as a image or an animation as if it was drawn by a hand
Home-page: https://github.com/dealfonso/pycanvashanddraw
Author: Carlos A.
Author-email: caralla@upv.es
License: Apache 2.0
Keywords: vector,canvas,hand drawing,drawing
Classifier: Development Status :: 5 - Production/Stable
Classifier: Intended Audience :: Science/Research
Classifier: Intended Audience :: End Users/Desktop
Classifier: Topic :: Scientific/Engineering :: Information Analysis
Classifier: Topic :: Scientific/Engineering :: Image Processing
Classifier: Topic :: Utilities
Classifier: Topic :: Multimedia :: Graphics
Classifier: Topic :: Multimedia :: Graphics :: Viewers
Classifier: License :: OSI Approved :: Apache Software License
Classifier: Programming Language :: Python :: 3
License-File: LICENSE
